bgboxmaker/__init__.py
bgboxmaker/main.py
bgboxmaker-0.0.1.dist-info/METADATA
bgboxmaker-0.0.1.dist-info/WHEEL
bgboxmaker-0.0.1.dist-info/licenses/LICENSE
bgboxmaker-0.0.1.dist-info/RECORD
