Metadata-Version: 2.4
Name: bgboxmaker
Version: 0.0.1
Summary: Board game tuck-box generator
Project-URL: Homepage, https://github.com/thetalorian/bgboxmaker
Author-email: Samuel Plum <splum@taloria.com>
License-Expression: MIT
License-File: LICENSE
Classifier: Operating System :: OS Independent
Classifier: Programming Language :: Python :: 3
Requires-Python: >=3.9
